.gitignore
005B.png
INSTALL.md
LICENSE
MANIFEST.in
Notes.md
README.md
README.rst
config.ini
junk.txt
requirements.txt
run_pyamiimage.py
satish_temp.png
setup.py
pyamiimage/__init__.py
pyamiimage/_old_ami_ocr.py
pyamiimage/_old_image_lib.py
pyamiimage/ami_arrow.py
pyamiimage/ami_easyocr.py
pyamiimage/ami_edge_manager.py
pyamiimage/ami_graph_all.py
pyamiimage/ami_image.py
pyamiimage/ami_ocr.py
pyamiimage/ami_plot.py
pyamiimage/ami_skeleton.py
pyamiimage/ami_util.py
pyamiimage/bbox.py
pyamiimage/cleaner.py
pyamiimage/commandline.py
pyamiimage/context.py
pyamiimage/flood_fill.py
pyamiimage/image_exploration.py
pyamiimage/imageanal.py
pyamiimage/octree.py
pyamiimage/sknw.py
pyamiimage/svg.py
pyamiimage/tesseract_hocr.py
pyamiimage/text_box.py
pyamiimage.egg-info/PKG-INFO
pyamiimage.egg-info/SOURCES.txt
pyamiimage.egg-info/dependency_links.txt
pyamiimage.egg-info/entry_points.txt
pyamiimage.egg-info/not-zip-safe
pyamiimage.egg-info/requires.txt
pyamiimage.egg-info/top_level.txt
pyamiimage/wrapper/__inti__.py
pyamiimage/wrapper/_for_easyocr.py
pyamiimage/wrapper/_for_tesseract.py
test/test_ami_graph.py
test/test_ami_image.py
test/test_ami_line_tool.py
test/test_ami_ocr.py
test/test_ami_skeleton.py
test/test_ami_util.py
test/test_arrow.py
test/test_bbox.py
test/test_colour_sep.py
test/test_image_tools.py
test/test_plots.py
test/test_svg.py
test/test_tesseract_hocr.py
test/test_text_box.py