Metadata-Version: 2.1
Name: pyamiimage
Version: 0.0.13
Summary: Image analysis for words and graphics.
Home-page: https://github.com/petermr/pyamiimage
Author: Peter Murray-Rust, Anuv Chakraborty
Author-email: petermurrayrust@googlemail.com
License: Apache2
Keywords: text and image mining
Platform: UNKNOWN
Classifier: Development Status :: 2 - Pre-Alpha
Classifier: Intended Audience :: Developers
Classifier: License :: OSI Approved :: Apache Software License
Classifier: Natural Language :: English
Classifier: Programming Language :: Python :: 3.4
Classifier: Programming Language :: Python :: 3.5
Classifier: Programming Language :: Python :: 3.6
Classifier: Programming Language :: Python :: 3.8
License-File: LICENSE
